linerate/__init__.py
linerate/model.py
linerate/py.typed
linerate/solver.py
linerate/types.py
linerate/units.py
linerate/equations/__init__.py
linerate/equations/convective_cooling.py
linerate/equations/dimensionless.py
linerate/equations/joule_heating.py
linerate/equations/math.py
linerate/equations/py.typed
linerate/equations/radiative_cooling.py
linerate/equations/solar_angles.py
linerate/equations/solar_heating.py
linerate/equations/cigre207/__init__.py
linerate/equations/cigre207/ac_resistance.py
linerate/equations/cigre207/convective_cooling.py
linerate/equations/cigre207/solar_heating.py
linerate/equations/cigre601/__init__.py
linerate/equations/cigre601/convective_cooling.py
linerate/equations/cigre601/py.typed
linerate/equations/cigre601/solar_heating.py
linerate/equations/ieee738/__init__.py
linerate/equations/ieee738/convective_cooling.py
linerate/equations/ieee738/py.typed
linerate/equations/ieee738/solar_heating.py
linerate/models/Cigre207.md
linerate/models/cigre207.py
linerate/models/cigre601.py
linerate/models/ieee738.py
linerate/models/thermal_model.py
linerate-2.2.1.dist-info/licenses/LICENSE
linerate-2.2.1.dist-info/METADATA
linerate-2.2.1.dist-info/WHEEL
linerate-2.2.1.dist-info/top_level.txt
linerate-2.2.1.dist-info/RECORD
