Metadata-Version: 2.4
Name: linerate
Version: 2.2.1
Summary: Library for computing line ampacity ratings for overhead lines
Author-email: Statnett Datascience <Datascience.Drift@Statnett.no>, Yngve Mardal Moe <yngve.m.moe@gmail.com>
Requires-Python: >=3.9
License-File: LICENSE
Requires-Dist: numpy
Requires-Dist: scipy
Requires-Dist: numba>=0.56.4
Requires-Dist: pygeodesy
Dynamic: license-file
